[
    {
        "nama_file": "city_night.png",
        "tanggal": "2026-05-19 10:18:03"
    },
    {
        "nama_file": "coffee_table.jpeg",
        "tanggal": "2026-05-19 10:26:25"
    },
    {
        "nama_file": "cyberpunk_city.png",
        "tanggal": "2026-05-19 20:58:14"
    },
    {
        "nama_file": "lilicantik.png",
        "tanggal": "2026-05-15 21:52:42"
    },
    {
        "nama_file": "midori.png",
        "tanggal": "2026-05-19 21:59:19"
    },
    {
        "nama_file": "old_camera.jpg",
        "tanggal": "2026-05-19 10:37:10"
    },
    {
        "nama_file": "retro_car.jpg",
        "tanggal": "2026-05-19 23:16:19"
    },
    {
        "nama_file": "sky_clouds.jpeg",
        "tanggal": "2026-05-19 10:33:48"
    },
    {
        "nama_file": "street_food.jpeg",
        "tanggal": "2026-05-19 10:46:44"
    },
    {
        "nama_file": "sunset_mountain.jpg",
        "tanggal": "2026-05-19 10:06:49"
    },
    {
        "nama_file": "workspace_dark.jpg",
        "tanggal": "2026-05-19 11:13:37"
    },
    {
        "nama_file": "waterfall_view.jpg",
        "tanggal": "2026-05-19 22:21:43"
    }
]